dask_opentelemetry/__about__.py
dask_opentelemetry/__init__.py
dask_opentelemetry-0.0.1a0.dist-info/METADATA
dask_opentelemetry-0.0.1a0.dist-info/WHEEL
dask_opentelemetry-0.0.1a0.dist-info/licenses/LICENSE.txt
dask_opentelemetry-0.0.1a0.dist-info/RECORD
