Metadata-Version: 2.1
Name: dask-opentelemetry
Version: 0.0.1a0
Summary: Instrument Dask with OpenTelemetry
Project-URL: Documentation, https://github.com/hendrikmakait/dask-opentelemetry#readme
Project-URL: Issues, https://github.com/hendrikmakait/dask-opentelemetry/issues
Project-URL: Source, https://github.com/hendrikmakait/dask-opentelemetry
Author-email: Hendrik Makait <hendrik@makait.com>
License-Expression: MIT
License-File: LICENSE.txt
Classifier: Programming Language :: Python
Classifier: Programming Language :: Python :: 3.8
Classifier: Programming Language :: Python :: 3.9
Classifier: Programming Language :: Python :: 3.10
Classifier: Programming Language :: Python :: 3.11
Requires-Python: <4.0,>=3.8
Requires-Dist: distributed>=2023.2.0
Requires-Dist: opentelemetry-api>=1.16.0
Requires-Dist: opentelemetry-sdk>=1.16.0
Requires-Dist: opentelemetry-semantic-conventions>=0.37b0
